converter/__init__.py
converter/config.py
converter/convert.py
converter/gui.py
gpt_convo_reader-0.2.3.dist-info/LICENSE
gpt_convo_reader-0.2.3.dist-info/METADATA
gpt_convo_reader-0.2.3.dist-info/WHEEL
gpt_convo_reader-0.2.3.dist-info/entry_points.txt
gpt_convo_reader-0.2.3.dist-info/top_level.txt
gpt_convo_reader-0.2.3.dist-info/RECORD
