Metadata-Version: 2.1
Name: gpt-convo-reader
Version: 0.2.3
Summary: Lets you find, view and format the conversations you've had with ChatGPT in the playground.
Home-page: https://github.com/romilly/gpt-convo-reader
Author: Romilly Cocking
Author-email: romilly.cocking@gmail.com
Project-URL: Bug Tracker, https://github.com/romilly/gpt-convo-reader/issues
Classifier: Programming Language :: Python :: 3
Classifier: License :: OSI Approved :: MIT License
Classifier: Operating System :: OS Independent
Requires-Python: >=3.10
License-File: LICENSE
Requires-Dist: guizero (>=1.4.0)
Requires-Dist: appdirs
